{"BRONCOS":{"id":10309072,"gameStartTimeLocalTime":"2022-10-06T20:15:00-04:00","homeTeam":"BRONCOS","awayTeam":"COLTS","homeScore":9,"awayScore":12,"timeLeft":"Final","gameOfWeek":false,"pickGame":true,"finalScore":true},"PACKERS":{"id":10293035,"gameStartTimeLocalTime":"2022-10-09T09:30:00-04:00","homeTeam":"PACKERS","awayTeam":"GIANTS","homeScore":0,"awayScore":0,"timeLeft":"Final","gameOfWeek":false,"pickGame":false,"finalScore":false},"BILLS":{"id":10309077,"gameStartTimeLocalTime":"2022-10-09T13:00:00-04:00","homeTeam":"BILLS","awayTeam":"STEELERS","homeScore":0,"awayScore":0,"timeLeft":"Final","gameOfWeek":false,"pickGame":false,"finalScore":false},"BROWNS":{"id":10309078,"gameStartTimeLocalTime":"2022-10-09T13:00:00-04:00","homeTeam":"BROWNS","awayTeam":"CHARGERS","homeScore":0,"awayScore":0,"timeLeft":"Final","gameOfWeek":false,"pickGame":false,"finalScore":false},"JAGUARS":{"id":10309079,"gameStartTimeLocalTime":"2022-10-09T13:00:00-04:00","homeTeam":"JAGUARS","awayTeam":"TEXANS","homeScore":0,"awayScore":0,"timeLeft":"Final","gameOfWeek":false,"pickGame":false,"finalScore":false},"VIKINGS":{"id":10309080,"gameStartTimeLocalTime":"2022-10-09T13:00:00-04:00","homeTeam":"VIKINGS","awayTeam":"BEARS","homeScore":0,"awayScore":0,"timeLeft":"Final","gameOfWeek":false,"pickGame":false,"finalScore":false},"PATRIOTS":{"id":10309073,"gameStartTimeLocalTime":"2022-10-09T13:00:00-04:00","homeTeam":"PATRIOTS","awayTeam":"LIONS","homeScore":0,"awayScore":0,"timeLeft":"Final","gameOfWeek":false,"pickGame":false,"finalScore":false},"SAINTS":{"id":10309074,"gameStartTimeLocalTime":"2022-10-09T13:00:00-04:00","homeTeam":"SAINTS","awayTeam":"SEAHAWKS","homeScore":0,"awayScore":0,"timeLeft":"Final","gameOfWeek":false,"pickGame":false,"finalScore":false},"JETS":{"id":10309075,"gameStartTimeLocalTime":"2022-10-09T13:00:00-04:00","homeTeam":"JETS","awayTeam":"DOLPHINS","homeScore":0,"awayScore":0,"timeLeft":"Final","gameOfWeek":false,"pickGame":false,"finalScore":false},"BUCCANEERS":{"id":10309076,"gameStartTimeLocalTime":"2022-10-09T13:00:00-04:00","homeTeam":"BUCCANEERS","awayTeam":"FALCONS","homeScore":0,"awayScore":0,"timeLeft":"Final","gameOfWeek":false,"pickGame":false,"finalScore":false},"COMMANDERS":{"id":10309081,"gameStartTimeLocalTime":"2022-10-09T13:00:00-04:00","homeTeam":"COMMANDERS","awayTeam":"TITANS","homeScore":0,"awayScore":0,"timeLeft":"Final","gameOfWeek":false,"pickGame":false,"finalScore":false},"PANTHERS":{"id":10309082,"gameStartTimeLocalTime":"2022-10-09T16:05:00-04:00","homeTeam":"PANTHERS","awayTeam":"49ERS","homeScore":0,"awayScore":0,"timeLeft":"Final","gameOfWeek":false,"pickGame":false,"finalScore":false},"CARDINALS":{"id":10309083,"gameStartTimeLocalTime":"2022-10-09T16:25:00-04:00","homeTeam":"CARDINALS","awayTeam":"EAGLES","homeScore":0,"awayScore":0,"timeLeft":"Final","gameOfWeek":false,"pickGame":false,"finalScore":false},"RAMS":{"id":10309084,"gameStartTimeLocalTime":"2022-10-09T16:25:00-04:00","homeTeam":"RAMS","awayTeam":"COWBOYS","homeScore":10,"awayScore":22,"timeLeft":"Final","gameOfWeek":true,"pickGame":true,"finalScore":true},"RAVENS":{"id":10309085,"gameStartTimeLocalTime":"2022-10-09T20:20:00-04:00","homeTeam":"RAVENS","awayTeam":"BENGALS","homeScore":19,"awayScore":17,"timeLeft":"Final","gameOfWeek":false,"pickGame":true,"finalScore":true},"CHIEFS":{"id":10309086,"gameStartTimeLocalTime":"2022-10-10T20:15:00-04:00","homeTeam":"CHIEFS","awayTeam":"RAIDERS","homeScore":28,"awayScore":27,"timeLeft":"Final","gameOfWeek":false,"pickGame":true,"finalScore":true}}